CHANGES.rst
DESCRIPTION.rst
LICENSE
MANIFEST.in
README.md
setup.py
src/sdc/sklearn/class_lister.py
src/sdc/sklearn/filter/__init__.py
src/sdc/sklearn/filter/_sklearn_predict.py
src/sdc/sklearn/writer/__init__.py
src/sdc/sklearn/writer/_sklearn_fit.py
src/spectral_data_converter_sklearn.egg-info/PKG-INFO
src/spectral_data_converter_sklearn.egg-info/SOURCES.txt
src/spectral_data_converter_sklearn.egg-info/dependency_links.txt
src/spectral_data_converter_sklearn.egg-info/entry_points.txt
src/spectral_data_converter_sklearn.egg-info/requires.txt
src/spectral_data_converter_sklearn.egg-info/top_level.txt